midealocal/__init__.py
midealocal/cli.py
midealocal/cloud.py
midealocal/const.py
midealocal/crc8.py
midealocal/device.py
midealocal/discover.py
midealocal/exceptions.py
midealocal/message.py
midealocal/packet_builder.py
midealocal/py.typed
midealocal/security.py
midealocal/version.py
midealocal/devices/__init__.py
midealocal/devices/a1/__init__.py
midealocal/devices/a1/message.py
midealocal/devices/ac/__init__.py
midealocal/devices/ac/message.py
midealocal/devices/b0/__init__.py
midealocal/devices/b0/message.py
midealocal/devices/b1/__init__.py
midealocal/devices/b1/message.py
midealocal/devices/b3/__init__.py
midealocal/devices/b3/message.py
midealocal/devices/b4/__init__.py
midealocal/devices/b4/message.py
midealocal/devices/b6/__init__.py
midealocal/devices/b6/message.py
midealocal/devices/b8/__init__.py
midealocal/devices/b8/const.py
midealocal/devices/b8/message.py
midealocal/devices/bf/__init__.py
midealocal/devices/bf/message.py
midealocal/devices/c2/__init__.py
midealocal/devices/c2/message.py
midealocal/devices/c3/__init__.py
midealocal/devices/c3/const.py
midealocal/devices/c3/message.py
midealocal/devices/ca/__init__.py
midealocal/devices/ca/message.py
midealocal/devices/cc/__init__.py
midealocal/devices/cc/message.py
midealocal/devices/cd/__init__.py
midealocal/devices/cd/message.py
midealocal/devices/ce/__init__.py
midealocal/devices/ce/message.py
midealocal/devices/cf/__init__.py
midealocal/devices/cf/message.py
midealocal/devices/da/__init__.py
midealocal/devices/da/message.py
midealocal/devices/db/__init__.py
midealocal/devices/db/message.py
midealocal/devices/dc/__init__.py
midealocal/devices/dc/message.py
midealocal/devices/e1/__init__.py
midealocal/devices/e1/message.py
midealocal/devices/e2/__init__.py
midealocal/devices/e2/message.py
midealocal/devices/e3/__init__.py
midealocal/devices/e3/message.py
midealocal/devices/e6/__init__.py
midealocal/devices/e6/message.py
midealocal/devices/e8/__init__.py
midealocal/devices/e8/message.py
midea_local_ben-6.1.0.dist-info/LICENSE
midea_local_ben-6.1.0.dist-info/METADATA
midea_local_ben-6.1.0.dist-info/WHEEL
midea_local_ben-6.1.0.dist-info/entry_points.txt
midea_local_ben-6.1.0.dist-info/top_level.txt
midea_local_ben-6.1.0.dist-info/RECORD
